generic_relations/__init__.py
generic_relations/relations.py
generic_relations/serializers.py
generic_relations/tests/__init__.py
generic_relations/tests/models.py
generic_relations/tests/test_relations.py
generic_relations/tests/test_serializers.py
generic_relations/tests/migrations/0001_initial.py
generic_relations/tests/migrations/__init__.py
rest_framework_generic_relations-2.2.0.dist-info/METADATA
rest_framework_generic_relations-2.2.0.dist-info/WHEEL
rest_framework_generic_relations-2.2.0.dist-info/top_level.txt
rest_framework_generic_relations-2.2.0.dist-info/RECORD
