Metadata-Version: 2.1
Name: rest-framework-generic-relations
Version: 2.2.0
Summary: Generic Relations for Django Rest Framework
Author: Lily Foote, Craig de Stigter
Project-URL: Source, https://github.com/craigds/rest-framework-generic-relations
Classifier: Environment :: Web Environment
Classifier: Framework :: Django
Classifier: Intended Audience :: Developers
Classifier: Operating System :: OS Independent
Classifier: Programming Language :: Python
Classifier: Programming Language :: Python :: 3.8
Classifier: Programming Language :: Python :: 3.9
Classifier: Programming Language :: Python :: 3.10
Classifier: Programming Language :: Python :: 3.11
Classifier: Programming Language :: Python :: 3.12
Classifier: Programming Language :: Python :: Implementation :: CPython
Classifier: Programming Language :: Python :: Implementation :: PyPy
Classifier: Framework :: Django :: 3.2
Classifier: Framework :: Django :: 4.2
Classifier: Framework :: Django :: 5.0
Classifier: License :: OSI Approved :: BSD License
Requires-Python: >=3.8
Requires-Dist: djangorestframework >=3.11.0
